dcp/__init__.py
dcp/estimator.py
dcp/job.py
dcp/storage.py
dcp/utils.py
dcp/tf_job_yaml/tf_job_base.yaml
dcp/tf_job_yaml/tf_job_dke.yaml
dcp/tf_job_yaml/tf_job_gke.yaml
dcp/tf_job_yaml/tf_job_tpu.yaml
dcp_sdk-0.0.15.dist-info/LICENSE
dcp_sdk-0.0.15.dist-info/METADATA
dcp_sdk-0.0.15.dist-info/WHEEL
dcp_sdk-0.0.15.dist-info/top_level.txt
dcp_sdk-0.0.15.dist-info/RECORD
